{
  "daily_counts": [
    {
      "date": "2026-04-18",
      "words": 101626
    },
    {
      "date": "2026-04-19",
      "words": 101626
    },
    {
      "date": "2026-04-20",
      "words": 101626
    },
    {
      "date": "2026-04-21",
      "words": 101626
    },
    {
      "date": "2026-04-22",
      "words": 102033
    },
    {
      "date": "2026-04-23",
      "words": 102033
    },
    {
      "date": "2026-04-24",
      "words": 102033
    },
    {
      "date": "2026-04-25",
      "words": 102748
    },
    {
      "date": "2026-04-26",
      "words": 102748
    },
    {
      "date": "2026-04-27",
      "words": 102748
    },
    {
      "date": "2026-04-28",
      "words": 102748
    },
    {
      "date": "2026-04-29",
      "words": 104760
    },
    {
      "date": "2026-04-30",
      "words": 104760
    },
    {
      "date": "2026-05-01",
      "words": 112483
    },
    {
      "date": "2026-05-02",
      "words": 112627
    },
    {
      "date": "2026-05-03",
      "words": 112627
    },
    {
      "date": "2026-05-04",
      "words": 112627
    },
    {
      "date": "2026-05-05",
      "words": 112758
    },
    {
      "date": "2026-05-06",
      "words": 112758
    },
    {
      "date": "2026-05-07",
      "words": 112758
    },
    {
      "date": "2026-05-08",
      "words": 125807
    },
    {
      "date": "2026-05-09",
      "words": 126161
    },
    {
      "date": "2026-05-10",
      "words": 126161
    },
    {
      "date": "2026-05-11",
      "words": 126161
    },
    {
      "date": "2026-05-12",
      "words": 126161
    },
    {
      "date": "2026-05-13",
      "words": 126161
    },
    {
      "date": "2026-05-14",
      "words": 126161
    },
    {
      "date": "2026-05-15",
      "words": 126161
    },
    {
      "date": "2026-05-16",
      "words": 126161
    },
    {
      "date": "2026-05-17",
      "words": 126161
    }
  ]
}